pytools/__init__.py
pytools/error.py
pytools/locals.py
pytoolstest-0.0.0.dist-info/LICENSE.txt
pytoolstest-0.0.0.dist-info/METADATA
pytoolstest-0.0.0.dist-info/WHEEL
pytoolstest-0.0.0.dist-info/top_level.txt
pytoolstest-0.0.0.dist-info/RECORD
