Metadata-Version: 2.1
Name: pytoolstest
Version: 0.0.0
Summary: free python tools
Home-page: https://www.cnblogs.com/7-pjk/
Author: BobLiang
Author-email: 1591609343@qq.com
License: MIT
Platform: UNKNOWN
Classifier: Topic :: Software Development :: Libraries :: Python Modules
Classifier: Programming Language :: Python :: 3
Classifier: Programming Language :: Python :: Implementation :: CPython
Requires-Dist: pygame (<=1.9.5)
Requires-Dist: requests
